LICENSE
MANIFEST.in
README.rst
pytest.ini
setup.py
tox.ini
examples/_threads.py
examples/cassandra_db.py
examples/crawler.py
examples/guv_simple_server.py
examples/logger.py
examples/pyuv_cffi_example.py
examples/threads.py
examples/wsgi_app.py
examples/guv/__init__.py
examples/guv/compat.py
examples/guv/const.py
examples/guv/event.py
examples/guv/exceptions.py
examples/guv/fileobject.py
examples/guv/greenio.py
examples/guv/greenpool.py
examples/guv/greenthread.py
examples/guv/patcher.py
examples/guv/queue.py
examples/guv/semaphore.py
examples/guv/server.py
examples/guv/timeout.py
examples/guv/websocket.py
examples/guv/wsgi.py
examples/guv/green/__init__.py
examples/guv/green/_socket3.py
examples/guv/green/_ssl32.py
examples/guv/green/_ssl33.py
examples/guv/green/builtin.py
examples/guv/green/greenlet_local.py
examples/guv/green/lock.py
examples/guv/green/os.py
examples/guv/green/queue.py
examples/guv/green/select.py
examples/guv/green/socket.py
examples/guv/green/ssl.py
examples/guv/green/subprocess.py
examples/guv/green/thread.py
examples/guv/green/threading.py
examples/guv/green/time.py
examples/guv/hubs/__init__.py
examples/guv/hubs/abc.py
examples/guv/hubs/hub.py
examples/guv/hubs/pyuv_cffi.py
examples/guv/hubs/switch.py
examples/guv/hubs/timer.py
examples/guv/support/__init__.py
examples/guv/support/cassandra.py
examples/guv/support/greendns.py
examples/guv/support/gunicorn_worker.py
examples/guv/support/psycopg2_patcher.py
examples/guv/util/__init__.py
examples/guv/util/debug.py
examples/guv/util/decorators.py
examples/guv/util/profile.py
examples/pyuv_cffi/__init__.py
guv/__init__.py
guv/compat.py
guv/const.py
guv/event.py
guv/exceptions.py
guv/fileobject.py
guv/greenio.py
guv/greenpool.py
guv/greenthread.py
guv/patcher.py
guv/queue.py
guv/semaphore.py
guv/server.py
guv/timeout.py
guv/websocket.py
guv/wsgi.py
guv.egg-info/PKG-INFO
guv.egg-info/SOURCES.txt
guv.egg-info/dependency_links.txt
guv.egg-info/not-zip-safe
guv.egg-info/requires.txt
guv.egg-info/top_level.txt
guv/green/__init__.py
guv/green/_socket3.py
guv/green/_ssl32.py
guv/green/_ssl33.py
guv/green/builtin.py
guv/green/greenlet_local.py
guv/green/lock.py
